hockeydata/__init__.py
hockeydata/api.py
hockeydata/constants.py
hockeydata/cli/__init__.py
hockeydata/cli/__main__.py
hockeydata/cli/utils.py
hockeydata/output/__init__.py
hockeydata/output/csv.py
hockeydata/output/json.py
hockeydata/output/pretty.py
hockeydata/output/text.py
hockeydata/scrape/__init__.py
hockeydata/scrape/common.py
hockeydata/scrape/html_pbp.py
hockeydata/scrape/html_roster.py
hockeydata/scrape/json_boxscore.py
hockeydata/scrape/json_pbp.py
hockeydata/scrape/json_schedule.py
hockeydata/scrape/json_shifts.py
hockeydata/scrape/players.py
hockeydata/scrape/scrape.py
hockeydata-0.0.3.dist-info/LICENSE.txt
hockeydata-0.0.3.dist-info/METADATA
hockeydata-0.0.3.dist-info/WHEEL
hockeydata-0.0.3.dist-info/entry_points.txt
hockeydata-0.0.3.dist-info/top_level.txt
hockeydata-0.0.3.dist-info/RECORD
