Metadata-Version: 2.1
Name: hockeydata
Version: 0.0.3
Summary: Library for accessing live hockey data to help analysts and hobbyists.
Home-page: https://github.com/adamfillion/hockeydata
Author: Adam Fillion
Author-email: adamfilliondev@gmail.com
License: UNKNOWN
Project-URL: Bug Reports, https://github.com/adamfillion/hockeydata/issues
Project-URL: Source, https://github.com/adamfillion/hockeydata/
Keywords: hockey data stats nhl nhlstats nhldata hockeystats hockeyapi nhlapi
Platform: UNKNOWN
Classifier: Development Status :: 3 - Alpha
Classifier: Intended Audience :: Developers
Classifier: Topic :: Software Development :: Build Tools
Classifier: License :: OSI Approved :: MIT License
Classifier: Programming Language :: Python :: 3.6
Classifier: Programming Language :: Python :: 3.7
Classifier: Programming Language :: Python :: 3.8
Requires-Python: >=3.5
Requires-Dist: Click
Requires-Dist: tabulate
Requires-Dist: pandas
Requires-Dist: requests
Requires-Dist: bs4
Requires-Dist: lxml
